[
    {
        "user_id": 12345,
        "isActive": true,
        "created_at": "2013-11-28T10:17:48 +05:00",
        "updated_at": "2014-01-09T05:03:30 +04:00"
    },
    {
        "user_id": 45654,
        "isActive": false,
        "created_at": "2012-10-16T18:18:53 +04:00",
        "updated_at": "2013-06-11T21:12:02 +04:00"
    },
    {
        "user_id": 66666,
        "isActive": true,
        "created_at": "2013-05-23T02:33:13 +04:00",
        "updated_at": "2013-07-05T23:35:54 +04:00"
    },
    {
        "user_id": 23415,
        "isActive": true,
        "created_at": "2013-02-23T16:54:37 +05:00",
        "updated_at": "2013-05-02T21:36:28 +04:00"
    },
    {
        "user_id": 78906,
        "isActive": true,
        "created_at": "2012-10-18T23:05:20 +04:00",
        "updated_at": "2013-02-26T07:10:40 +05:00"
    }
]